gitty/__init__.py
gitty/gitty_color.py
gitty/gitty_command.py
gitty/gitty_command_clean.py
gitty/gitty_command_head.py
gitty/gitty_command_help.py
gitty/gitty_command_parent.py
gitty/gitty_command_plugins.py
gitty/gitty_command_release.py
gitty/gitty_command_show.py
gitty/gitty_command_task.py
gitty/gitty_command_version.py
gitty/gitty_executor.py
gitty/gitty_git_api.py
gitty/gitty_project_type.py
gitty/gitty_project_type_gradle_kotlin.py
gitty/gitty_project_type_maven.py
gitty/gitty_project_type_node.py
gitty/gitty_project_type_pip.py
gitty/gitty_project_type_xcode.py
gitty/gitty_support.py
gitty/gitty_xml_tree_builder.py
gitty-1.8.0.data/scripts/_gitty_completion.zsh
gitty-1.8.0.data/scripts/gitty
gitty-1.8.0.data/scripts/gitty_completion.zsh
plugin_samples/finish_task.py
plugin_samples/merge_check.py
plugin_samples/pull_request.py
plugin_samples/zsh_complete.py
gitty-1.8.0.dist-info/METADATA
gitty-1.8.0.dist-info/WHEEL
gitty-1.8.0.dist-info/top_level.txt
gitty-1.8.0.dist-info/RECORD
