Metadata-Version: 2.1
Name: gitty
Version: 1.8.0
Summary: An alternate git workflow tool
Home-page: https://github.com/lmeadors/gitty
Author: Larry Meadors
Author-email: larry.meadors@elm-software.com
Classifier: Programming Language :: Python :: 3
Classifier: License :: OSI Approved :: MIT License
Classifier: Operating System :: OS Independent
Requires-Python: >=3.6
